{"Connection":{"AgentId":4,"AutoLogin":false,"CheckForJobs":{"Units":2,"Value":15},"ClientProxy":{"Domain":"","Password":"","Port":80,"RequiresAuth":false,"Server":"","Type":1,"UseDefaultCredentials":false,"Username":""},"Domain":"va-gov.domo.com","EncryptedApiKey":"","EncryptedPassword":"","IgnoreCertErrors":false,"Server":"https://va-gov.domo.com","UseApiKey":false,"UseOAuth":true,"Username":"","Valid":true,"WaitForIndexing":false},"DataSource":{"UpdateMode":0,"DataSourceId":"12157dc6-2de0-413e-9c9e-df1d1c8cef7d","LastVersion":0,"Name":"IAM AuthDB - latest snapshot","SourceType":"workbench-csv","Description":null,"ForceNew":false,"UploadUnchanged":false,"ClearOnEmptyResults":false,"MultiPartUpload":null,"ExecutionLimit":2,"SelectedPartitionGrain":0,"StreamID":1109,"PartitionColumnID":null,"IsPartitionCaseSensitive":false},"WorkbenchConfig":{"Hash":"865TbJOjH8cORDWTd4orn3sO03d69JQ5VARphyDS6jg=","HashVersion":6,"IsHighBandwidth":false,"LastExecution":{"DataHash":"5306c674","ExecutionMessage":"Successfully sent 17,821,110 data rows to Domo.","LastUpdateMode":0,"ReaderExecutionTimespan":2000584,"RowsUpdated":17821110,"Successful":true,"TotalExecutionTimespan":2083649,"TransferExecutionTimespan":53766},"DataSourceId":"12157dc6-2de0-413e-9c9e-df1d1c8cef7d","DataHandling":0,"DataSourceConfig":null,"DataSource":{"UpdateMode":0,"DataSourceId":"12157dc6-2de0-413e-9c9e-df1d1c8cef7d","LastVersion":0,"Name":"IAM AuthDB - latest snapshot","SourceType":"workbench-csv","Description":null,"ForceNew":false,"UploadUnchanged":false,"ClearOnEmptyResults":false,"MultiPartUpload":null,"ExecutionLimit":2,"SelectedPartitionGrain":0,"StreamID":1109,"PartitionColumnID":null,"IsPartitionCaseSensitive":false},"NotificationSettings":{"SuccessUserList":[],"ErrorUserList":[],"JobSummaryUserList":[]},"ErrorHandling":{"Mode":1},"DataReader":{"ReaderType":"DomoDataReaders.CsvDataReader.CsvDataReader","Properties":null},"DataProvider":{"ProviderType":"DomoDataProviders.LocalFileProvider.LocalFileDataProvider","Properties":{"FileName":"C:\\Users\\vacodickss\\ETL\\1 extracted\\AuthDB Data\\CSPID_ACTIVE_20250609\\CSPID_ACTIVE_20250609.csv"}},"Transforms":[{"ColumnId":"b81c5f7c-1d03-47e1-b778-86445bfd4fa4","Columns":[],"IsActive":false,"Properties":{"SearchColumn":"CSPID","SearchValue":"^(?<csp>.*?)_.*$","ReplaceValue":"${csp}","AlternateValue":null},"TransformType":"DomoDataTransforms.SearchReplace.SearchReplaceDataTransform","Type":null},{"ColumnId":"91b36210-fff6-493b-9dc6-9d1c13b31f19","Columns":[],"IsActive":false,"Properties":{"Column":"CSPID","FilterQuery":"^(DSLogon|200DOD|200VIDM|200VLGN|200MH|idme)$","ExcludeFilter":false,"FilterOnNull":true},"TransformType":"DomoDataTransforms.FilterTransform.FilterDataTransform","Type":null},{"ColumnId":"891d1a55-31d9-4b0f-bedc-ef70dad23da3","Columns":[],"IsActive":false,"Properties":{"HashType":0,"HashedColumns":["SECID"],"MigratedFromV3":false},"TransformType":"DomoDataTransforms.HashValueTransform.HashValueTransform","Type":null},{"ColumnId":"a2511e0d-d139-4d8f-8c0d-605719e490f7","Columns":[],"IsActive":false,"Properties":{"HashType":0,"HashedColumns":["MVIICN"],"MigratedFromV3":false},"TransformType":"DomoDataTransforms.HashValueTransform.HashValueTransform","Type":null},{"ColumnId":"46615b93-233b-4c11-9e0a-a247b9abf601","Columns":[],"IsActive":false,"Properties":{"Calculation":"TODAY","ColumnName":"SNAPSHOT_DATE","Version":0},"TransformType":"DomoDataTransforms.CalculatedField.CalculatedFieldTransform","Type":null}],"DataSchema":{"Columns":[{"Include":true,"UserOverride":false,"SourceColumn":"SECID","TransformId":null,"ColumnType":0,"ColumnId":"d8a10d5e-1f2f-4c80-a145-d13dc69fbac7","DataTypeLocked":false,"DestinationColumn":"SECID","name":"SECID","type":"STRING","metadata":{"isEncrypted":false},"UpsertKey":false,"LockColumn":true,"SoftDelete":false,"TypeSetFromPlugin":true},{"Include":true,"UserOverride":false,"SourceColumn":"MVIICN","TransformId":null,"ColumnType":0,"ColumnId":"d3f5794b-05a3-48e6-903f-d00e0febe02d","DataTypeLocked":false,"DestinationColumn":"MVIICN","name":"MVIICN","type":"STRING","metadata":{"isEncrypted":false},"UpsertKey":false,"LockColumn":true,"SoftDelete":false,"TypeSetFromPlugin":true},{"Include":false,"UserOverride":false,"SourceColumn":"FIRSTNAME","TransformId":null,"ColumnType":0,"ColumnId":"f7c30cee-f3cb-4c9a-b113-a8f3c03a8b17","DataTypeLocked":false,"DestinationColumn":"FIRSTNAME","name":"FIRSTNAME","type":"STRING","metadata":{"isEncrypted":false},"UpsertKey":false,"LockColumn":true,"SoftDelete":false,"TypeSetFromPlugin":false},{"Include":false,"UserOverride":false,"SourceColumn":"LASTNAME","TransformId":null,"ColumnType":0,"ColumnId":"e44dd769-f4b9-4f8f-b7e3-b876a8932add","DataTypeLocked":false,"DestinationColumn":"LASTNAME","name":"LASTNAME","type":"STRING","metadata":{"isEncrypted":false},"UpsertKey":false,"LockColumn":true,"SoftDelete":false,"TypeSetFromPlugin":false},{"Include":true,"UserOverride":false,"SourceColumn":"CSPID","TransformId":null,"ColumnType":0,"ColumnId":"d3df0b38-7e6a-4801-b228-8e1f7e110f19","DataTypeLocked":false,"DestinationColumn":"CSPID","name":"CSPID","type":"STRING","metadata":{"isEncrypted":false},"UpsertKey":false,"LockColumn":true,"SoftDelete":false,"TypeSetFromPlugin":false},{"Include":false,"UserOverride":false,"SourceColumn":"STATUS","TransformId":null,"ColumnType":0,"ColumnId":"21d091bc-9f1e-41ed-bbc9-5f6c5fd56d1c","DataTypeLocked":false,"DestinationColumn":"STATUS","name":"STATUS","type":"STRING","metadata":{"isEncrypted":false},"UpsertKey":false,"LockColumn":true,"SoftDelete":false,"TypeSetFromPlugin":false},{"Include":true,"UserOverride":false,"SourceColumn":"LAST_USED","TransformId":null,"ColumnType":0,"ColumnId":"2ccf6404-aa34-4fd1-bb35-fce5b9262039","DataTypeLocked":false,"DestinationColumn":"LAST_USED","name":"LAST_USED","type":"DATE","metadata":{"isEncrypted":false},"UpsertKey":false,"LockColumn":true,"SoftDelete":false,"TypeSetFromPlugin":false},{"Include":false,"UserOverride":false,"SourceColumn":"IAL","TransformId":null,"ColumnType":0,"ColumnId":"4547cc40-4c54-4e0e-aead-02c3dc38a85e","DataTypeLocked":false,"DestinationColumn":"IAL","name":"IAL","type":"NONE","metadata":{"isEncrypted":false},"UpsertKey":false,"LockColumn":true,"SoftDelete":false,"TypeSetFromPlugin":false},{"Include":false,"UserOverride":false,"SourceColumn":"AAL","TransformId":null,"ColumnType":0,"ColumnId":"def7fac1-f244-4ad7-8cca-41f74004a207","DataTypeLocked":false,"DestinationColumn":"AAL","name":"AAL","type":"NONE","metadata":{"isEncrypted":false},"UpsertKey":false,"LockColumn":true,"SoftDelete":false,"TypeSetFromPlugin":false},{"Include":false,"UserOverride":false,"SourceColumn":"FAL","TransformId":null,"ColumnType":0,"ColumnId":"36404e8d-166f-4146-81a1-640c140a7ee4","DataTypeLocked":false,"DestinationColumn":"FAL","name":"FAL","type":"NONE","metadata":{"isEncrypted":false},"UpsertKey":false,"LockColumn":true,"SoftDelete":false,"TypeSetFromPlugin":false},{"Include":true,"UserOverride":false,"SourceColumn":"CSP_METHOD","TransformId":null,"ColumnType":0,"ColumnId":"7e6938cf-a3c6-4847-b670-2cec79155b46","DataTypeLocked":false,"DestinationColumn":"CSP_METHOD","name":"CSP_METHOD","type":"STRING","metadata":{"isEncrypted":false},"UpsertKey":false,"LockColumn":true,"SoftDelete":false,"TypeSetFromPlugin":false},{"Include":true,"UserOverride":false,"SourceColumn":"RECORD_CREATED_DATE","TransformId":"d28cc28e-1c5b-48ab-b351-552625d76596","ColumnType":1,"ColumnId":"61cf793c-e910-441d-b4f8-85b86304dfae","DataTypeLocked":true,"DestinationColumn":"RECORD_CREATED_DATE","name":"RECORD_CREATED_DATE","type":"DATE","metadata":{"isEncrypted":false},"UpsertKey":false,"LockColumn":true,"SoftDelete":false,"TypeSetFromPlugin":false},{"Include":false,"UserOverride":false,"SourceColumn":"VAEMAIL","TransformId":null,"ColumnType":0,"ColumnId":"f35d12d5-8f51-4495-96df-7dedbed6d402","DataTypeLocked":false,"DestinationColumn":"VAEMAIL","name":"VAEMAIL","type":"STRING","metadata":{"isEncrypted":false},"UpsertKey":false,"LockColumn":true,"SoftDelete":false,"TypeSetFromPlugin":false},{"Include":false,"UserOverride":false,"SourceColumn":"EXTERNALEMAIL","TransformId":null,"ColumnType":0,"ColumnId":"72239148-30f1-4d46-9c30-483e774815cd","DataTypeLocked":false,"DestinationColumn":"EXTERNALEMAIL","name":"EXTERNALEMAIL","type":"STRING","metadata":{"isEncrypted":false},"UpsertKey":false,"LockColumn":true,"SoftDelete":false,"TypeSetFromPlugin":false},{"Include":true,"UserOverride":false,"SourceColumn":"SNAPSHOT_DATE","TransformId":"f65c9013-9700-4bae-aa1c-3780a35025ab","ColumnType":1,"ColumnId":"46615b93-233b-4c11-9e0a-a247b9abf601","DataTypeLocked":true,"DestinationColumn":"SNAPSHOT_DATE","name":"SNAPSHOT_DATE","type":"DATE","metadata":{"isEncrypted":false},"UpsertKey":false,"LockColumn":true,"SoftDelete":false,"TypeSetFromPlugin":false}],"EmptySchema":false},"ConfigVersion":5,"Impersonation":{"EncryptionVersion":1,"RequiresImpersonation":false},"UseFileWatcher":false,"Disabled":false,"DisabledReason":0,"ExtendedDisabledReason":null,"WaitForAdrenalineProcessing":true,"AdvancedScheduleEnabled":false,"EncryptionVersion":1,"ConvertNullStrings":false,"SchemaChangeHandling":0,"DataCloud":null},"agentId":4,"configType":"application/json","created":1737994441567,"executionTimeout":24,"id":85,"config":"{\"Hash\":\"XkBsSvfxnt/HfqoOXlhW66vYrzWg+QKwBYx3ifeAsvk=\",\"HashVersion\":6,\"IsHighBandwidth\":false,\"LastExecution\":{\"DataHash\":\"5306c674\",\"ExecutionMessage\":\"Successfully sent 17,821,110 data rows to Domo.\",\"LastUpdateMode\":0,\"ReaderExecutionTimespan\":2000584,\"RowsUpdated\":17821110,\"Successful\":true,\"TotalExecutionTimespan\":2083649,\"TransferExecutionTimespan\":53766},\"DataSourceId\":\"12157dc6-2de0-413e-9c9e-df1d1c8cef7d\",\"DataHandling\":0,\"DataSourceConfig\":null,\"DataSource\":{\"UpdateMode\":0,\"DataSourceId\":\"12157dc6-2de0-413e-9c9e-df1d1c8cef7d\",\"LastVersion\":0,\"Name\":\"IAM MPI - latest snapshot\",\"SourceType\":\"workbench-csv\",\"Description\":null,\"ForceNew\":false,\"UploadUnchanged\":false,\"ClearOnEmptyResults\":false,\"MultiPartUpload\":null,\"ExecutionLimit\":2,\"SelectedPartitionGrain\":0,\"StreamID\":1109,\"PartitionColumnID\":null,\"IsPartitionCaseSensitive\":false},\"NotificationSettings\":{\"SuccessUserList\":[\"sdickson@greenthreadsllc.com\"],\"ErrorUserList\":[\"sdickson@greenthreadsllc.com\"],\"JobSummaryUserList\":[]},\"ErrorHandling\":{\"Mode\":1},\"DataReader\":{\"ReaderType\":\"DomoDataReaders.CsvDataReader.CsvDataReader\",\"Properties\":null},\"DataProvider\":{\"ProviderType\":\"DomoDataProviders.LocalFileProvider.LocalFileDataProvider\",\"Properties\":{\"FileName\":\"C:\\\\Users\\\\vacodickss\\\\ETL\\\\1 extracted\\\\AuthDB Data\\\\CSPID_ACTIVE_20250609\\\\CSPID_ACTIVE_20250609.csv\"}},\"Transforms\":[{\"ColumnId\":\"b81c5f7c-1d03-47e1-b778-86445bfd4fa4\",\"Columns\":[],\"IsActive\":false,\"Properties\":{\"SearchColumn\":\"CSPID\",\"SearchValue\":\"^(?<csp>.*?)_.*$\",\"ReplaceValue\":\"${csp}\",\"AlternateValue\":null},\"TransformType\":\"DomoDataTransforms.SearchReplace.SearchReplaceDataTransform\",\"Type\":null},{\"ColumnId\":\"91b36210-fff6-493b-9dc6-9d1c13b31f19\",\"Columns\":[],\"IsActive\":false,\"Properties\":{\"Column\":\"CSPID\",\"FilterQuery\":\"^(DSLogon|200DOD|200VIDM|200VLGN|200MH|idme)$\",\"ExcludeFilter\":false,\"FilterOnNull\":true},\"TransformType\":\"DomoDataTransforms.FilterTransform.FilterDataTransform\",\"Type\":null},{\"ColumnId\":\"891d1a55-31d9-4b0f-bedc-ef70dad23da3\",\"Columns\":[],\"IsActive\":false,\"Properties\":{\"HashType\":0,\"HashedColumns\":[\"SECID\"],\"MigratedFromV3\":false},\"TransformType\":\"DomoDataTransforms.HashValueTransform.HashValueTransform\",\"Type\":null},{\"ColumnId\":\"a2511e0d-d139-4d8f-8c0d-605719e490f7\",\"Columns\":[],\"IsActive\":false,\"Properties\":{\"HashType\":0,\"HashedColumns\":[\"MVIICN\"],\"MigratedFromV3\":false},\"TransformType\":\"DomoDataTransforms.HashValueTransform.HashValueTransform\",\"Type\":null},{\"ColumnId\":\"46615b93-233b-4c11-9e0a-a247b9abf601\",\"Columns\":[],\"IsActive\":false,\"Properties\":{\"Calculation\":\"TODAY\",\"ColumnName\":\"SNAPSHOT_DATE\",\"Version\":0},\"TransformType\":\"DomoDataTransforms.CalculatedField.CalculatedFieldTransform\",\"Type\":null}],\"DataSchema\":{\"Columns\":[{\"Include\":true,\"UserOverride\":false,\"SourceColumn\":\"SECID\",\"TransformId\":null,\"ColumnType\":0,\"ColumnId\":\"d8a10d5e-1f2f-4c80-a145-d13dc69fbac7\",\"DataTypeLocked\":false,\"DestinationColumn\":\"SECID\",\"name\":\"SECID\",\"type\":\"STRING\",\"metadata\":{\"isEncrypted\":false},\"UpsertKey\":false,\"LockColumn\":true,\"SoftDelete\":false,\"TypeSetFromPlugin\":true},{\"Include\":true,\"UserOverride\":false,\"SourceColumn\":\"MVIICN\",\"TransformId\":null,\"ColumnType\":0,\"ColumnId\":\"d3f5794b-05a3-48e6-903f-d00e0febe02d\",\"DataTypeLocked\":false,\"DestinationColumn\":\"MVIICN\",\"name\":\"MVIICN\",\"type\":\"STRING\",\"metadata\":{\"isEncrypted\":false},\"UpsertKey\":false,\"LockColumn\":true,\"SoftDelete\":false,\"TypeSetFromPlugin\":true},{\"Include\":false,\"UserOverride\":false,\"SourceColumn\":\"FIRSTNAME\",\"TransformId\":null,\"ColumnType\":0,\"ColumnId\":\"f7c30cee-f3cb-4c9a-b113-a8f3c03a8b17\",\"DataTypeLocked\":false,\"DestinationColumn\":\"FIRSTNAME\",\"name\":\"FIRSTNAME\",\"type\":\"STRING\",\"metadata\":{\"isEncrypted\":false},\"UpsertKey\":false,\"LockColumn\":true,\"SoftDelete\":false,\"TypeSetFromPlugin\":false},{\"Include\":false,\"UserOverride\":false,\"SourceColumn\":\"LASTNAME\",\"TransformId\":null,\"ColumnType\":0,\"ColumnId\":\"e44dd769-f4b9-4f8f-b7e3-b876a8932add\",\"DataTypeLocked\":false,\"DestinationColumn\":\"LASTNAME\",\"name\":\"LASTNAME\",\"type\":\"STRING\",\"metadata\":{\"isEncrypted\":false},\"UpsertKey\":false,\"LockColumn\":true,\"SoftDelete\":false,\"TypeSetFromPlugin\":false},{\"Include\":true,\"UserOverride\":false,\"SourceColumn\":\"CSPID\",\"TransformId\":null,\"ColumnType\":0,\"ColumnId\":\"d3df0b38-7e6a-4801-b228-8e1f7e110f19\",\"DataTypeLocked\":false,\"DestinationColumn\":\"CSPID\",\"name\":\"CSPID\",\"type\":\"STRING\",\"metadata\":{\"isEncrypted\":false},\"UpsertKey\":false,\"LockColumn\":true,\"SoftDelete\":false,\"TypeSetFromPlugin\":false},{\"Include\":false,\"UserOverride\":false,\"SourceColumn\":\"STATUS\",\"TransformId\":null,\"ColumnType\":0,\"ColumnId\":\"21d091bc-9f1e-41ed-bbc9-5f6c5fd56d1c\",\"DataTypeLocked\":false,\"DestinationColumn\":\"STATUS\",\"name\":\"STATUS\",\"type\":\"STRING\",\"metadata\":{\"isEncrypted\":false},\"UpsertKey\":false,\"LockColumn\":true,\"SoftDelete\":false,\"TypeSetFromPlugin\":false},{\"Include\":true,\"UserOverride\":false,\"SourceColumn\":\"LAST_USED\",\"TransformId\":null,\"ColumnType\":0,\"ColumnId\":\"2ccf6404-aa34-4fd1-bb35-fce5b9262039\",\"DataTypeLocked\":false,\"DestinationColumn\":\"LAST_USED\",\"name\":\"LAST_USED\",\"type\":\"DATE\",\"metadata\":{\"isEncrypted\":false},\"UpsertKey\":false,\"LockColumn\":true,\"SoftDelete\":false,\"TypeSetFromPlugin\":false},{\"Include\":false,\"UserOverride\":false,\"SourceColumn\":\"IAL\",\"TransformId\":null,\"ColumnType\":0,\"ColumnId\":\"4547cc40-4c54-4e0e-aead-02c3dc38a85e\",\"DataTypeLocked\":false,\"DestinationColumn\":\"IAL\",\"name\":\"IAL\",\"type\":\"NONE\",\"metadata\":{\"isEncrypted\":false},\"UpsertKey\":false,\"LockColumn\":true,\"SoftDelete\":false,\"TypeSetFromPlugin\":false},{\"Include\":false,\"UserOverride\":false,\"SourceColumn\":\"AAL\",\"TransformId\":null,\"ColumnType\":0,\"ColumnId\":\"def7fac1-f244-4ad7-8cca-41f74004a207\",\"DataTypeLocked\":false,\"DestinationColumn\":\"AAL\",\"name\":\"AAL\",\"type\":\"NONE\",\"metadata\":{\"isEncrypted\":false},\"UpsertKey\":false,\"LockColumn\":true,\"SoftDelete\":false,\"TypeSetFromPlugin\":false},{\"Include\":false,\"UserOverride\":false,\"SourceColumn\":\"FAL\",\"TransformId\":null,\"ColumnType\":0,\"ColumnId\":\"36404e8d-166f-4146-81a1-640c140a7ee4\",\"DataTypeLocked\":false,\"DestinationColumn\":\"FAL\",\"name\":\"FAL\",\"type\":\"NONE\",\"metadata\":{\"isEncrypted\":false},\"UpsertKey\":false,\"LockColumn\":true,\"SoftDelete\":false,\"TypeSetFromPlugin\":false},{\"Include\":true,\"UserOverride\":false,\"SourceColumn\":\"CSP_METHOD\",\"TransformId\":null,\"ColumnType\":0,\"ColumnId\":\"7e6938cf-a3c6-4847-b670-2cec79155b46\",\"DataTypeLocked\":false,\"DestinationColumn\":\"CSP_METHOD\",\"name\":\"CSP_METHOD\",\"type\":\"STRING\",\"metadata\":{\"isEncrypted\":false},\"UpsertKey\":false,\"LockColumn\":true,\"SoftDelete\":false,\"TypeSetFromPlugin\":false},{\"Include\":true,\"UserOverride\":false,\"SourceColumn\":\"RECORD_CREATED_DATE\",\"TransformId\":\"d28cc28e-1c5b-48ab-b351-552625d76596\",\"ColumnType\":1,\"ColumnId\":\"61cf793c-e910-441d-b4f8-85b86304dfae\",\"DataTypeLocked\":true,\"DestinationColumn\":\"RECORD_CREATED_DATE\",\"name\":\"RECORD_CREATED_DATE\",\"type\":\"DATE\",\"metadata\":{\"isEncrypted\":false},\"UpsertKey\":false,\"LockColumn\":true,\"SoftDelete\":false,\"TypeSetFromPlugin\":false},{\"Include\":false,\"UserOverride\":false,\"SourceColumn\":\"VAEMAIL\",\"TransformId\":null,\"ColumnType\":0,\"ColumnId\":\"f35d12d5-8f51-4495-96df-7dedbed6d402\",\"DataTypeLocked\":false,\"DestinationColumn\":\"VAEMAIL\",\"name\":\"VAEMAIL\",\"type\":\"STRING\",\"metadata\":{\"isEncrypted\":false},\"UpsertKey\":false,\"LockColumn\":true,\"SoftDelete\":false,\"TypeSetFromPlugin\":false},{\"Include\":false,\"UserOverride\":false,\"SourceColumn\":\"EXTERNALEMAIL\",\"TransformId\":null,\"ColumnType\":0,\"ColumnId\":\"72239148-30f1-4d46-9c30-483e774815cd\",\"DataTypeLocked\":false,\"DestinationColumn\":\"EXTERNALEMAIL\",\"name\":\"EXTERNALEMAIL\",\"type\":\"STRING\",\"metadata\":{\"isEncrypted\":false},\"UpsertKey\":false,\"LockColumn\":true,\"SoftDelete\":false,\"TypeSetFromPlugin\":false},{\"Include\":true,\"UserOverride\":false,\"SourceColumn\":\"SNAPSHOT_DATE\",\"TransformId\":\"f65c9013-9700-4bae-aa1c-3780a35025ab\",\"ColumnType\":1,\"ColumnId\":\"46615b93-233b-4c11-9e0a-a247b9abf601\",\"DataTypeLocked\":true,\"DestinationColumn\":\"SNAPSHOT_DATE\",\"name\":\"SNAPSHOT_DATE\",\"type\":\"DATE\",\"metadata\":{\"isEncrypted\":false},\"UpsertKey\":false,\"LockColumn\":true,\"SoftDelete\":false,\"TypeSetFromPlugin\":false}],\"EmptySchema\":false},\"ConfigVersion\":5,\"Impersonation\":{\"EncryptionVersion\":1,\"RequiresImpersonation\":false},\"UseFileWatcher\":false,\"Disabled\":false,\"DisabledReason\":0,\"ExtendedDisabledReason\":null,\"WaitForAdrenalineProcessing\":true,\"AdvancedScheduleEnabled\":false,\"EncryptionVersion\":1,\"ConvertNullStrings\":false,\"SchemaChangeHandling\":0,\"DataCloud\":null}","lastRun":1749480887149,"lastSuccessfulRun":1749480887149,"modified":1749494541153,"name":"IAM AuthDB - All Active Credentials - Weekly","nextRun":null,"schedule":null}